LICENSE
MANIFEST.in
README.rst
setup.py
webhose/__init__.py
webhose.egg-info/PKG-INFO
webhose.egg-info/SOURCES.txt
webhose.egg-info/dependency_links.txt
webhose.egg-info/requires.txt
webhose.egg-info/top_level.txt