Metadata-Version: 1.1
Name: webhose
Version: 0.1.2
Summary: Simple client library for the webhose.io REST API
Home-page: https://github.com/Buzzilla/webhose-python
Author: Israel Tsadok
Author-email: itsadok@gmail.com
License: MIT
Platform: UNKNOWN
Classifier: Development Status :: 4 - Beta
Classifier: Intended Audience :: Developers
Classifier: Natural Language :: English
Classifier: License :: OSI Approved :: MIT License
Classifier: Programming Language :: Python
Classifier: Programming Language :: Python :: 2.6
Classifier: Programming Language :: Python :: 2.7
Classifier: Programming Language :: Python :: 3
Classifier: Programming Language :: Python :: 3.3
Classifier: Programming Language :: Python :: 3.4
